[
  {
    "name": "Flower | Doobie Labs | Blue Lobster",
    "img": "https://images.dutchie.com/flower-stock-9-v1.jpg?auto=format%2Ccompress&cs=srgb&fit=max&fill=solid&fillColor=%23fff&ixlib=react-9.8.1&h=188&w=188",
    "brand": "Doobies",
    "link": "https://ocdispensary.github.io/oc-dispensary/menu?dtche%5Bproduct%5D=flower-doobie-labs-blue-lobster",
    "price": "$54.00"
  },
  {
    "name": "Infused Pre-Rolls | Ayrloom | Cereal Milk - 5pk",
    "img": "https://images.dutchie.com/626005be2ffca52d395c956306b82dee?auto=format%2Ccompress&cs=srgb&fit=max&fill=solid&fillColor=%23fff&ixlib=react-9.8.1&h=188&w=188",
    "brand": "ayrloom",
    "link": "https://ocdispensary.github.io/oc-dispensary/menu?dtche%5Bproduct%5D=infused-pre-rolls-ayrloom-cereal-milk-5pk",
    "price": "$40.00"
  },
  {
    "name": "Ayrloom | Mood Rest | AIO | 1g | THC : CBN",
    "img": "https://images.dutchie.com/a072d213793b45a8bc2073459c691fb7?auto=format%2Ccompress&cs=srgb&fit=max&fill=solid&fillColor=%23fff&ixlib=react-9.8.1&h=188&w=188",
    "brand": "ayrloom",
    "link": "https://ocdispensary.github.io/oc-dispensary/menu?dtche%5Bproduct%5D=ayrloom-mood-rest-aio-1g-thc-cbn-28243",
    "price": "$50.00"
  },
  {
    "name": "Flower | Platinum Reserve | Titan OG",
    "img": "https://images.dutchie.com/73d4a987f22f6c1c43196a0cb32e55e3?auto=format%2Ccompress&cs=srgb&fit=max&fill=solid&fillColor=%23fff&ixlib=react-9.8.1&h=188&w=188",
    "brand": "Platinum Reserve",
    "link": "https://ocdispensary.github.io/oc-dispensary/menu?dtche%5Bproduct%5D=flower-platinum-reserve-titan-og",
    "price": "$46.00"
  },
  {
    "name": "Ayrloom | Mood Focus | AIO | 1g | THC : THCV",
    "img": "https://images.dutchie.com/3d01f30c99e9ebdf1a801cb0badc0c88?auto=format%2Ccompress&cs=srgb&fit=max&fill=solid&fillColor=%23fff&ixlib=react-9.8.1&h=188&w=188",
    "brand": "ayrloom",
    "link": "https://ocdispensary.github.io/oc-dispensary/menu?dtche%5Bproduct%5D=ayrloom-mood-focus-aio-1g-thc-thcv-71184",
    "price": "$50.00"
  },
  {
    "name": "Vape AIO | Eureka | Mango Haze",
    "img": "https://images.dutchie.com/8b0fdb7ee8a8445aa41b1f7bce5bfada?auto=format%2Ccompress&cs=srgb&fit=max&fill=solid&fillColor=%23fff&ixlib=react-9.8.1&h=188&w=188",
    "brand": "Eureka",
    "link": "https://ocdispensary.github.io/oc-dispensary/menu?dtche%5Bproduct%5D=vape-aio-eureka-mango-haze",
    "price": "$65.00"
  },
  {
    "name": "Pre-Rolls | Uncle Budd NYC | Mixed 6pk",
    "img": "https://images.dutchie.com/790edc8c58551370a9632c59f809f851?auto=format%2Ccompress&cs=srgb&fit=max&fill=solid&fillColor=%23fff&ixlib=react-9.8.1&h=188&w=188",
    "brand": "Uncle Budd NYC",
    "link": "https://ocdispensary.github.io/oc-dispensary/menu?dtche%5Bproduct%5D=pre-rolls-uncle-budd-nyc-mixed-6pk",
    "price": "$54.00"
  },
  {
    "name": "Concentrate | BLOX | Grape Bubblegum Rosin Badder",
    "img": "https://images.dutchie.com/f24891fff171a33206e8a2a2434b2bef?auto=format%2Ccompress&cs=srgb&fit=max&fill=solid&fillColor=%23fff&ixlib=react-9.8.1&h=188&w=188",
    "brand": "BLOX",
    "link": "https://ocdispensary.github.io/oc-dispensary/menu?dtche%5Bproduct%5D=concentrate-blox-grape-bubblegum-rosin-badder",
    "price": "$80.00"
  },
  {
    "name": "Flower | Gypsy Weed | Amnesia",
    "img": "https://images.dutchie.com/flower-stock-5-v1.jpg?auto=format%2Ccompress&cs=srgb&fit=max&fill=solid&fillColor=%23fff&ixlib=react-9.8.1&h=188&w=188",
    "brand": "Gypsy Weed",
    "link": "https://ocdispensary.github.io/oc-dispensary/menu?dtche%5Bproduct%5D=flower-gypsy-weed-amnesia",
    "price": "$160.00"
  },
  {
    "name": "Ayrloom | Pineapple Express | AIO | 0.5g",
    "img": "https://images.dutchie.com/6385a3ecba6560be2695106ad722c7a8?auto=format%2Ccompress&cs=srgb&fit=max&fill=solid&fillColor=%23fff&ixlib=react-9.8.1&h=188&w=188",
    "brand": "ayrloom",
    "link": "https://ocdispensary.github.io/oc-dispensary/menu?dtche%5Bproduct%5D=ayrloom-pineapple-express-aio-0-5g-25793",
    "price": "$30.00"
  },
  {
    "name": "Infused Flower | Her Highness | Doggy Bag",
    "img": "https://images.dutchie.com/bcb80a871f8002ffbe4b533572ad802c?auto=format%2Ccompress&cs=srgb&fit=max&fill=solid&fillColor=%23fff&ixlib=react-9.8.1&h=188&w=188",
    "brand": "HER Highness",
    "link": "https://ocdispensary.github.io/oc-dispensary/menu?dtche%5Bproduct%5D=infused-flower-her-highness-doggy-bag",
    "price": "$50.00"
  },
  {
    "name": "Flower | Pura | Blue Dream X Purple Punch",
    "img": "https://images.dutchie.com/flower-stock-6-v1.jpg?auto=format%2Ccompress&cs=srgb&fit=max&fill=solid&fillColor=%23fff&ixlib=react-9.8.1&h=188&w=188",
    "brand": "Pura",
    "link": "https://ocdispensary.github.io/oc-dispensary/menu?dtche%5Bproduct%5D=flower-pura-blue-dream-x-purple-punch",
    "price": "$150.00"
  },
  {
    "name": "Vape AIO | Jaunty | Blue Dream",
    "img": "https://images.dutchie.com/5dbfe950e70f4c74bea2b18b4989d6eb?auto=format%2Ccompress&cs=srgb&fit=max&fill=solid&fillColor=%23fff&ixlib=react-9.8.1&h=188&w=188",
    "brand": "Jaunty",
    "link": "https://ocdispensary.github.io/oc-dispensary/menu?dtche%5Bproduct%5D=vape-aio-jaunty-blue-dream",
    "price": "$60.00"
  },
  {
    "name": "Flower | Revert | Pineapple Haze",
    "img": "https://images.dutchie.com/a52d59f1611564ef6b084aa890f86ccb?auto=format%2Ccompress&cs=srgb&fit=max&fill=solid&fillColor=%23fff&ixlib=react-9.8.1&h=188&w=188",
    "brand": "Revert",
    "link": "https://ocdispensary.github.io/oc-dispensary/menu?dtche%5Bproduct%5D=flower-revert-pineapple-haze",
    "price": "$30.00"
  },
  {
    "name": "Vape Pod | Rove | RELOAD 2pk - Pineapple Express",
    "img": "https://images.dutchie.com/6af319cb6faea3f5873dbc7b28f5a4f9?auto=format%2Ccompress&cs=srgb&fit=max&fill=solid&fillColor=%23fff&ixlib=react-9.8.1&h=188&w=188",
    "brand": "Rove",
    "link": "https://ocdispensary.github.io/oc-dispensary/menu?dtche%5Bproduct%5D=vape-pod-rove-reload-2pk-pineapple-express",
    "price": "$114.00"
  },
  {
    "name": "Pre Rolls | Ruby Farms | Sour Diesel- 7pk",
    "img": "https://images.dutchie.com/9b8bb82d420d6ce7163300eac538eb82?auto=format%2Ccompress&cs=srgb&fit=max&fill=solid&fillColor=%23fff&ixlib=react-9.8.1&h=188&w=188",
    "brand": "Ruby Farms",
    "link": "https://ocdispensary.github.io/oc-dispensary/menu?dtche%5Bproduct%5D=pre-rolls-ruby-farms-sour-diesel-7pk",
    "price": "$38.00"
  },
  {
    "name": "Flower | Zizzle | Silver Haze",
    "img": "https://images.dutchie.com/a241e9f10aa7219b822fe5e4acf360a4?auto=format%2Ccompress&cs=srgb&fit=max&fill=solid&fillColor=%23fff&ixlib=react-9.8.1&h=188&w=188",
    "brand": "Zizzle",
    "link": "https://ocdispensary.github.io/oc-dispensary/menu?dtche%5Bproduct%5D=flower-zizzle-silver-haze",
    "price": "$54.00"
  },
  {
    "name": "DANK MIMOSA 5PK 2.75G",
    "img": "https://images.dutchie.com/9c298e473b6d1e454df94d015f187dd8?auto=format%2Ccompress&cs=srgb&fit=max&fill=solid&fillColor=%23fff&ixlib=react-9.8.1&h=188&w=188",
    "brand": "Dank By Definition.",
    "link": "https://ocdispensary.github.io/oc-dispensary/menu?dtche%5Bproduct%5D=dank-mimosa-5pk-2-75g",
    "price": "$50.00"
  },
  {
    "name": "Ayrloom | Mood Energy | AIO | 1g | THC : THCV : CBG",
    "img": "https://images.dutchie.com/e7c5dfcad6c2de84f434f83279704083?auto=format%2Ccompress&cs=srgb&fit=max&fill=solid&fillColor=%23fff&ixlib=react-9.8.1&h=188&w=188",
    "brand": "ayrloom",
    "link": "https://ocdispensary.github.io/oc-dispensary/menu?dtche%5Bproduct%5D=ayrloom-mood-energy-aio-1g-thc-thcv-cbg-80470",
    "price": "$50.00"
  },
  {
    "name": "Flower | Flower House | Jack Diesel",
    "img": "https://images.dutchie.com/4066a102c5ef86f838aac7384eabcae7?auto=format%2Ccompress&cs=srgb&fit=max&fill=solid&fillColor=%23fff&ixlib=react-9.8.1&h=188&w=188",
    "brand": "FlowerHouse",
    "link": "https://ocdispensary.github.io/oc-dispensary/menu?dtche%5Bproduct%5D=flower-flower-house-jack-diesel",
    "price": "$49.00"
  },
  {
    "name": "Infused Pre Roll | Flower House | Biscotti 2pk",
    "img": "https://images.dutchie.com/4066a102c5ef86f838aac7384eabcae7?auto=format%2Ccompress&cs=srgb&fit=max&fill=solid&fillColor=%23fff&ixlib=react-9.8.1&h=188&w=188",
    "brand": "FlowerHouse",
    "link": "https://ocdispensary.github.io/oc-dispensary/menu?dtche%5Bproduct%5D=infused-pre-roll-flower-house-biscotti-2pk",
    "price": "$12.00"
  },
  {
    "name": "VAPE AIO | Cannabals | Live Diamonds Vape - Banana OG",
    "img": "https://images.dutchie.com/eeef7acde6e77b2d50a9ee0fcb2cdc1e?auto=format%2Ccompress&cs=srgb&fit=max&fill=solid&fillColor=%23fff&ixlib=react-9.8.1&h=188&w=188",
    "brand": "Cannabals",
    "link": "https://ocdispensary.github.io/oc-dispensary/menu?dtche%5Bproduct%5D=vape-aio-cannabals-live-diamonds-vape-banana-og",
    "price": "$90.00"
  },
  {
    "name": "Vape AIO | Ayrloom | Pink Rozay",
    "img": "https://images.dutchie.com/cf417c866d65002d97e9d9caf312b58c?auto=format%2Ccompress&cs=srgb&fit=max&fill=solid&fillColor=%23fff&ixlib=react-9.8.1&h=188&w=188",
    "brand": "ayrloom",
    "link": "https://ocdispensary.github.io/oc-dispensary/menu?dtche%5Bproduct%5D=vape-aio-ayrloom-pink-rozay",
    "price": "$30.00"
  },
  {
    "name": "Flower | Revert | Pink Starburst",
    "img": "https://images.dutchie.com/b4c9521d9f2ccf6234a21f2abedccdc5?auto=format%2Ccompress&cs=srgb&fit=max&fill=solid&fillColor=%23fff&ixlib=react-9.8.1&h=188&w=188",
    "brand": "Revert",
    "link": "https://ocdispensary.github.io/oc-dispensary/menu?dtche%5Bproduct%5D=flower-revert-pink-starburst",
    "price": "$30.00"
  },
  {
    "name": "Vape AIO | Fernway | Alpine Strawberry",
    "img": "https://images.dutchie.com/a5ea0ac6a6f3cffec8cdf7dbf45106c1?auto=format%2Ccompress&cs=srgb&fit=max&fill=solid&fillColor=%23fff&ixlib=react-9.8.1&h=188&w=188",
    "brand": "Fernway",
    "link": "https://ocdispensary.github.io/oc-dispensary/menu?dtche%5Bproduct%5D=vape-aio-fernway-alpine-strawberry",
    "price": "$90.00"
  }
]